odoo9_addon_sale_order_digitized_signature-9.0.1.0.0-py2.7-nspkg.pth
odoo9_addon_sale_order_digitized_signature-9.0.1.0.0.dist-info/DESCRIPTION.rst
odoo9_addon_sale_order_digitized_signature-9.0.1.0.0.dist-info/METADATA
odoo9_addon_sale_order_digitized_signature-9.0.1.0.0.dist-info/RECORD
odoo9_addon_sale_order_digitized_signature-9.0.1.0.0.dist-info/WHEEL
odoo9_addon_sale_order_digitized_signature-9.0.1.0.0.dist-info/metadata.json
odoo9_addon_sale_order_digitized_signature-9.0.1.0.0.dist-info/namespace_packages.txt
odoo9_addon_sale_order_digitized_signature-9.0.1.0.0.dist-info/top_level.txt
odoo_addons/sale_order_digitized_signature/README.rst
odoo_addons/sale_order_digitized_signature/__init__.py
odoo_addons/sale_order_digitized_signature/__openerp__.py
odoo_addons/sale_order_digitized_signature/i18n/es.po
odoo_addons/sale_order_digitized_signature/models/__init__.py
odoo_addons/sale_order_digitized_signature/models/sale.py
odoo_addons/sale_order_digitized_signature/report/report_saleorder.xml
odoo_addons/sale_order_digitized_signature/static/description/icon.png
odoo_addons/sale_order_digitized_signature/views/sale_views.xml
